odoo/addons/purchase_split_by_route/README.rst
odoo/addons/purchase_split_by_route/__init__.py
odoo/addons/purchase_split_by_route/__manifest__.py
odoo/addons/purchase_split_by_route/i18n/it.po
odoo/addons/purchase_split_by_route/i18n/purchase_split_by_route.pot
odoo/addons/purchase_split_by_route/models/__init__.py
odoo/addons/purchase_split_by_route/models/purchase_order.py
odoo/addons/purchase_split_by_route/models/stock_route.py
odoo/addons/purchase_split_by_route/models/stock_rule.py
odoo/addons/purchase_split_by_route/readme/CONTRIBUTORS.rst
odoo/addons/purchase_split_by_route/readme/DESCRIPTION.rst
odoo/addons/purchase_split_by_route/static/description/icon.png
odoo/addons/purchase_split_by_route/static/description/index.html
odoo/addons/purchase_split_by_route/tests/__init__.py
odoo/addons/purchase_split_by_route/tests/test_purchase_route.py
odoo/addons/purchase_split_by_route/views/stock_route.xml
odoo_addon_purchase_split_by_route-16.0.1.0.0.4.dist-info/METADATA
odoo_addon_purchase_split_by_route-16.0.1.0.0.4.dist-info/WHEEL
odoo_addon_purchase_split_by_route-16.0.1.0.0.4.dist-info/top_level.txt
odoo_addon_purchase_split_by_route-16.0.1.0.0.4.dist-info/RECORD
